ASDCache/ASDCache.py
ASDCache/__init__.py
ASDCache/_version.py
asdcache-0.2.2.dist-info/METADATA
asdcache-0.2.2.dist-info/WHEEL
asdcache-0.2.2.dist-info/licenses/LICENSE
asdcache-0.2.2.dist-info/RECORD
