Metadata-Version: 2.4
Name: ASDCache
Version: 0.2.2
Summary: A Python module to retrieve data from the NIST Atomic Spectra Database (ASD), using caching for fast, efficient data handling
Project-URL: Documentation, https://antoinetue.github.io/asdcache
Project-URL: Source, https://github.com/AntoineTUE/asdcache
Author-email: Antoine Salden <t.p.w.salden@tue.nl>
License: MIT
License-File: LICENSE
Keywords: ASD,Atomic Spectra Database,NIST,atoms,spectra,spectroscopy,spectrum
Classifier: Development Status :: 4 - Beta
Classifier: Intended Audience :: Science/Research
Classifier: License :: OSI Approved :: MIT License
Classifier: Operating System :: OS Independent
Classifier: Programming Language :: Python :: 3.9
Classifier: Programming Language :: Python :: 3.10
Classifier: Programming Language :: Python :: 3.11
Classifier: Programming Language :: Python :: 3.12
Classifier: Programming Language :: Python :: 3.13
Classifier: Topic :: Scientific/Engineering
Requires-Python: >=3.9
Requires-Dist: bs4
Requires-Dist: numpy
Requires-Dist: pandas
Requires-Dist: requests
Requires-Dist: requests-cache
Provides-Extra: docs
Requires-Dist: black; extra == 'docs'
Requires-Dist: mkdocs; extra == 'docs'
Requires-Dist: mkdocs-autorefs; extra == 'docs'
Requires-Dist: mkdocs-gen-files; extra == 'docs'
Requires-Dist: mkdocs-git-revision-date-localized-plugin; extra == 'docs'
Requires-Dist: mkdocs-include-markdown-plugin; extra == 'docs'
Requires-Dist: mkdocs-jupyter; extra == 'docs'
Requires-Dist: mkdocs-literate-nav; extra == 'docs'
Requires-Dist: mkdocs-material; extra == 'docs'
Requires-Dist: mkdocs-section-index; extra == 'docs'
Requires-Dist: mkdocstrings; extra == 'docs'
Requires-Dist: mkdocstrings-python; extra == 'docs'
Provides-Extra: polars
Requires-Dist: polars; extra == 'polars'
